[{
    "avr_id": "h415p956r",
    "title": "Agnes Cashman Dance Films",
    "id": "156cbe8f-3973-4b5b-a76e-d7625a1880fc",
    "admin_email": null,
    "description": "Agnes Cashman is a former Northwestern University professor of dance. She became director of physical education in the College of Liberal Arts in 1932. The following year, she was named director of Orchesis, the honorary dance organization. The three films in this collection, which have been digitized from 16mm reels, document dance performances that are believed to be of Cashman.",
    "featured": false,
    "finding_aid_url": null,
    "published": true,
    "keywords": [],
    "visibility": {
      "id": "RESTRICTED",
      "scheme": "visibility"
    },
    "reading_room": null
  },
  {
    "avr_id": "mg74qn63p",
    "title": "Arnold Jacobs Master Class Audio Archives",
    "id": "fbe609ee-0fab-472d-bc98-51dce3077167",
    "admin_email": null,
    "description": "",
    "featured": false,
    "finding_aid_url": null,
    "published": true,
    "keywords": [],
    "visibility": {
      "id": "OPEN",
      "scheme": "visibility"
    },
    "reading_room": null
  },
  {
    "avr_id": "6q182k21g",
    "title": "Asher Golden Collection",
    "id": "f65b3ae2-e4a9-40b7-b0a0-b48416eae767",
    "admin_email": null,
    "description": null,
    "featured": false,
    "finding_aid_url": null,
    "published": true,
    "keywords": [],
    "visibility": {
      "id": "OPEN",
      "scheme": "visibility"
    },
    "reading_room": null
  },
  {
    "avr_id": "t148fj751",
    "title": "Berkeley Folk Music Festival",
    "id": "18ec4c6b-192a-4ab8-9903-ea0f393c35f7",
    "admin_email": null,
    "description": "",
    "featured": false,
    "finding_aid_url": null,
    "published": true,
    "keywords": [],
    "visibility": {
      "id": "OPEN",
      "scheme": "visibility"
    },
    "reading_room": null
  },
  {
    "avr_id": "n009w378w",
    "title": "Bursar's Office Collection",
    "id": "1be8bea9-b37d-4450-9c15-87ea2c049f2c",
    "admin_email": null,
    "description": "",
    "featured": false,
    "finding_aid_url": null,
    "published": true,
    "keywords": [],
    "visibility": {
      "id": "OPEN",
      "scheme": "visibility"
    },
    "reading_room": null
  },
  {
    "avr_id": "dz010r42j",
    "title": "Chicago Chamber Musicians Archive, 1989-2010",
    "id": "2933302a-a629-4e3b-81ed-db7a54b33a8c",
    "admin_email": null,
    "description": "Audio recordings of Chicago Chamber Musicians concerts and performances. ",
    "featured": false,
    "finding_aid_url": null,
    "published": true,
    "keywords": [],
    "visibility": {
      "id": "RESTRICTED",
      "scheme": "visibility"
    },
    "reading_room": null
  },
  {
    "avr_id": "hq37vn63r",
    "title": "Dave Eanet Collection",
    "id": "6e4ade35-1212-4c07-bf90-de5b1e9965b1",
    "admin_email": null,
    "description": null,
    "featured": false,
    "finding_aid_url": null,
    "published": true,
    "keywords": [],
    "visibility": {
      "id": "RESTRICTED",
      "scheme": "visibility"
    },
    "reading_room": null
  },
  {
    "avr_id": "2b88qd78p",
    "title": "Dick Higgins Archive",
    "id": "4cebd3f7-94d1-4ecc-96d0-ab173c99c8f4",
    "admin_email": null,
    "description": "",
    "featured": false,
    "finding_aid_url": null,
    "published": true,
    "keywords": [],
    "visibility": {
      "id": "RESTRICTED",
      "scheme": "visibility"
    },
    "reading_room": 0
  },
  {
    "avr_id": "hd76s164m",
    "title": "Donald and Vera Ward Audio",
    "id": "41ab2a18-4a4d-41e1-b9f1-7e020991656a",
    "admin_email": null,
    "description": "",
    "featured": false,
    "finding_aid_url": null,
    "published": true,
    "keywords": [],
    "visibility": {
      "id": "AUTHENTICATED",
      "scheme": "visibility"
    },
    "reading_room": null
  },
  {
    "avr_id": "d504rn02k",
    "title": "Donald and Vera Ward Films",
    "id": "8d4b9dca-8298-4554-9539-c635b63143f0",
    "admin_email": null,
    "description": "",
    "featured": false,
    "finding_aid_url": null,
    "published": true,
    "keywords": [],
    "visibility": {
      "id": "AUTHENTICATED",
      "scheme": "visibility"
    },
    "reading_room": null
  },
  {
    "avr_id": "v405sb99h",
    "title": "Electroacoustic Music Collection",
    "id": "ce486ac5-3895-42d7-972c-d3ed78521f10",
    "admin_email": null,
    "description": "",
    "featured": false,
    "finding_aid_url": null,
    "published": true,
    "keywords": [],
    "visibility": {
      "id": "AUTHENTICATED",
      "scheme": "visibility"
    },
    "reading_room": null
  },
  {
    "avr_id": "7w62f825p",
    "title": "Herskovits Library of African Studies Audiovisual Collection",
    "id": "3ebceea3-a68e-450d-ab86-c773c79d7173",
    "admin_email": null,
    "description": "",
    "featured": false,
    "finding_aid_url": null,
    "published": true,
    "keywords": [],
    "visibility": {
      "id": "AUTHENTICATED",
      "scheme": "visibility"
    },
    "reading_room": null
  },
  {
    "avr_id": "1j92g748c",
    "title": "Imagination without Borders",
    "id": "d389d9ca-27e3-44fc-a12f-3a5a4208a6c8",
    "admin_email": null,
    "description": null,
    "featured": false,
    "finding_aid_url": null,
    "published": true,
    "keywords": [],
    "visibility": {
      "id": "RESTRICTED",
      "scheme": "visibility"
    },
    "reading_room": null
  },
  {
    "avr_id": "js956f81p",
    "title": "J. Rothfuss Topless Cellist Archive",
    "id": "462fbe40-20e3-43b0-8960-ffc4d71f6fdf",
    "admin_email": null,
    "description": null,
    "featured": false,
    "finding_aid_url": null,
    "published": false,
    "keywords": [],
    "visibility": {
      "id": "RESTRICTED",
      "scheme": "visibility"
    },
    "reading_room": null
  },
  {
    "avr_id": "gf06g405t",
    "title": "Leigh Bienen Videos",
    "id": "442cc5c7-2c72-481c-a84f-eca6ef976505",
    "admin_email": null,
    "description": "",
    "featured": false,
    "finding_aid_url": null,
    "published": true,
    "keywords": [],
    "visibility": {
      "id": "OPEN",
      "scheme": "visibility"
    },
    "reading_room": null
  },
  {
    "avr_id": "qj72p719f",
    "title": "McCormick Library of Special Collections Audiovisual Collection",
    "id": "8fdc5942-12a0-4abd-8f43-5d19b37ece75",
    "admin_email": null,
    "description": "",
    "featured": false,
    "finding_aid_url": null,
    "published": true,
    "keywords": [],
    "visibility": {
      "id": "RESTRICTED",
      "scheme": "visibility"
    },
    "reading_room": null
  },
  {
    "avr_id": "xg94hr111",
    "title": "Northwestern University Basketball Films",
    "id": "dea85d0c-9601-4190-be6b-ce8e0aa68302",
    "admin_email": null,
    "description": "",
    "featured": false,
    "finding_aid_url": null,
    "published": true,
    "keywords": [],
    "visibility": {
      "id": "AUTHENTICATED",
      "scheme": "visibility"
    },
    "reading_room": null
  },
  {
    "avr_id": "h415p952n",
    "title": "Northwestern University Football Films",
    "id": "8cdf83c9-3831-4211-acd7-122bca9b89da",
    "admin_email": null,
    "description": null,
    "featured": false,
    "finding_aid_url": null,
    "published": true,
    "keywords": [],
    "visibility": {
      "id": "OPEN",
      "scheme": "visibility"
    },
    "reading_room": null
  },
  {
    "avr_id": "8049g5061",
    "title": "Northwestern University Marching Band",
    "id": "a5309704-fd07-437d-9a4f-f65ce53dd272",
    "admin_email": null,
    "description": "",
    "featured": false,
    "finding_aid_url": null,
    "published": true,
    "keywords": [],
    "visibility": {
      "id": "OPEN",
      "scheme": "visibility"
    },
    "reading_room": null
  },
  {
    "avr_id": "x633f261f",
    "title": "Northwestern University School of Commerce Building Demolition Films",
    "id": "dec40c20-70ec-4303-a579-8d992627f7ad",
    "admin_email": null,
    "description": "",
    "featured": false,
    "finding_aid_url": null,
    "published": true,
    "keywords": [],
    "visibility": {
      "id": "OPEN",
      "scheme": "visibility"
    },
    "reading_room": null
  },
  {
    "avr_id": "dz010q765",
    "title": "Northwestern University School of Music Concert Recordings",
    "id": "0fa71404-cc94-4a51-be46-6124ebf0d201",
    "admin_email": null,
    "description": "",
    "featured": false,
    "finding_aid_url": null,
    "published": true,
    "keywords": [],
    "visibility": {
      "id": "AUTHENTICATED",
      "scheme": "visibility"
    },
    "reading_room": null
  },
  {
    "avr_id": "rf55z927z",
    "title": "NU Libraries",
    "id": "d2ae687b-d180-4600-8b1a-886c0cf35e79",
    "admin_email": "",
    "description": "",
    "featured": false,
    "finding_aid_url": "",
    "published": true,
    "keywords": [],
    "visibility": {
      "id": "OPEN",
      "scheme": "visibility"
    },
    "reading_room": null
  },
  {
    "avr_id": "zc77sq117",
    "title": "Otto Graham Collection",
    "id": "6180f90c-8205-445a-af94-b9c8ce3f6dc5",
    "admin_email": null,
    "description": null,
    "featured": false,
    "finding_aid_url": null,
    "published": true,
    "keywords": [],
    "visibility": {
      "id": "AUTHENTICATED",
      "scheme": "visibility"
    },
    "reading_room": null
  },
  {
    "avr_id": "np193919g",
    "title": "Poetry and Poetics Colloquium",
    "id": "5f6e9e67-7f2d-4208-b3bd-b1aedcdf7e35",
    "admin_email": null,
    "description": null,
    "featured": false,
    "finding_aid_url": null,
    "published": true,
    "keywords": [],
    "visibility": {
      "id": "RESTRICTED",
      "scheme": "visibility"
    },
    "reading_room": null
  },
  {
    "avr_id": "pz50gx667",
    "title": "Project Survival Films, 1970",
    "id": "f359687a-e496-404b-8708-9bbe490521dd",
    "admin_email": null,
    "description": "",
    "featured": false,
    "finding_aid_url": null,
    "published": true,
    "keywords": [],
    "visibility": {
      "id": "OPEN",
      "scheme": "visibility"
    },
    "reading_room": null
  },
  {
    "avr_id": "00000137v",
    "title": "Ray Still Master Class Audio Archives",
    "id": "eaa3047f-685b-4a52-8e38-e11e4792faba",
    "admin_email": null,
    "description": "",
    "featured": false,
    "finding_aid_url": null,
    "published": true,
    "keywords": [],
    "visibility": {
      "id": "AUTHENTICATED",
      "scheme": "visibility"
    },
    "reading_room": null
  },
  {
    "avr_id": "4q77fs89p",
    "title": "Robert Greenfield Archive",
    "id": "ec153e6d-a543-4b50-a7dc-ae5e98a27129",
    "admin_email": null,
    "description": "",
    "featured": false,
    "finding_aid_url": null,
    "published": true,
    "keywords": [],
    "visibility": {
      "id": "RESTRICTED",
      "scheme": "visibility"
    },
    "reading_room": null
  },
  {
    "avr_id": "5t34sm44f",
    "title": "Robert Lefley Audio Collection",
    "id": "c31e4fd4-6f5c-4156-9343-3f73d147b668",
    "admin_email": null,
    "description": "",
    "featured": false,
    "finding_aid_url": null,
    "published": true,
    "keywords": [],
    "visibility": {
      "id": "OPEN",
      "scheme": "visibility"
    },
    "reading_room": null
  },
  {
    "avr_id": "47429917w",
    "title": "Robert Marcellus Master Class Audio Archives",
    "id": "48cefdba-c111-4a6a-8d40-98ba7986e2d6",
    "admin_email": null,
    "description": null,
    "featured": false,
    "finding_aid_url": null,
    "published": true,
    "keywords": [],
    "visibility": {
      "id": "OPEN",
      "scheme": "visibility"
    },
    "reading_room": null
  },
  {
    "avr_id": "j098zb66k",
    "title": "Student Event Films",
    "id": "bd4846b7-5370-4c92-acea-8ea6a04894d2",
    "admin_email": null,
    "description": "The copyright and related rights status of this collection have not been evaluated. Due to the sensitive nature of some of the material in this collection it has been made dark.  Future access and visibility of this collection will require consultation with University Archives, university communications and upper administration.",
    "featured": false,
    "finding_aid_url": null,
    "published": true,
    "keywords": [],
    "visibility": {
      "id": "RESTRICTED",
      "scheme": "visibility"
    },
    "reading_room": null
  },
  {
    "avr_id": "tb09j567x",
    "title": "The Dharma Talks of Kongo Langlois Roshi",
    "id": "58432865-db82-4b05-8910-453fe1df5972",
    "admin_email": null,
    "description": null,
    "featured": false,
    "finding_aid_url": null,
    "published": true,
    "keywords": [],
    "visibility": {
      "id": "OPEN",
      "scheme": "visibility"
    },
    "reading_room": null
  },
  {
    "avr_id": "0r967441j",
    "title": "Transportation Library Audiovisual Collection",
    "id": "aab3574c-e17d-43f2-93ab-fb6298bc0fc5",
    "admin_email": null,
    "description": "",
    "featured": false,
    "finding_aid_url": null,
    "published": true,
    "keywords": [],
    "visibility": {
      "id": "OPEN",
      "scheme": "visibility"
    },
    "reading_room": null
  },
  {
    "avr_id": "6d56zw66p",
    "title": "University Archives Audiovisual Media",
    "id": "c3ced30c-3e7c-4762-99bf-52809483885f",
    "admin_email": null,
    "description": null,
    "featured": false,
    "finding_aid_url": null,
    "published": true,
    "keywords": [],
    "visibility": {
      "id": "RESTRICTED",
      "scheme": "visibility"
    },
    "reading_room": null
  },
  {
    "avr_id": "ns064705k",
    "title": "Vincent Cichowicz Master Class Audio Archives",
    "id": "5c9eaad8-afb8-4224-ae1a-cffddc731109",
    "admin_email": null,
    "description": "",
    "featured": false,
    "finding_aid_url": null,
    "published": true,
    "keywords": [],
    "visibility": {
      "id": "OPEN",
      "scheme": "visibility"
    },
    "reading_room": null
  },
  {
    "avr_id": "c247dt58b",
    "title": "Viola Spolin Video Collection",
    "id": "b840ae13-705e-4caf-b711-95f170465ea7",
    "admin_email": null,
    "description": "These Audio/Visual Materials are part of the Viola Spolin Papers. \r\nhttps://findingaids.library.northwestern.edu/repositories/7/resources/238",
    "featured": false,
    "finding_aid_url": null,
    "published": true,
    "keywords": [],
    "visibility": {
      "id": "RESTRICTED",
      "scheme": "visibility"
    },
    "reading_room": 0
  },
  {
    "avr_id": "vq27zn46v",
    "title": "Waa-Mu Show Audiovisual Recordings",
    "id": "e2a8b9db-1807-4bbf-aa76-2b2487dc887f",
    "admin_email": null,
    "description": "The copyright and related rights status of this collection have not been evaluated. Due to the sensitive nature of some of the material in this collection it has been made dark.  Future access and visibility of this collection will require consultation with University Archives, university communications and upper administration.",
    "featured": false,
    "finding_aid_url": null,
    "published": true,
    "keywords": [],
    "visibility": {
      "id": "RESTRICTED",
      "scheme": "visibility"
    },
    "reading_room": null
  },
  {
    "avr_id": "1v53jx07z",
    "title": "Waa-Mu Show Collection",
    "id": "7bdf5966-4621-4088-ac1f-91a45d9a7036",
    "admin_email": null,
    "description": null,
    "featured": false,
    "finding_aid_url": null,
    "published": true,
    "keywords": [],
    "visibility": {
      "id": "RESTRICTED",
      "scheme": "visibility"
    },
    "reading_room": null
  }
]